kern/__init__.py
kern/__main__.py
kern/magic.py
kern/doc/__init__.py
kern/doc/bin.py
kern/doc/lib.py
kern/html/__init__.py
kern/html/bin.py
kern/html/lib.py
kern/image/__init__.py
kern/image/bin/__init__.py
kern/image/lib/__init__.py
kern/image/lib/image.py
kern/image/lib/image_and_text.py
kern/pdf/__init__.py
kern/pdf/bin.py
kern/pdf/lib.py
kern/video/__init__.py
kern/video/bin.py
kern/video/lib.py
kern-0.0.14.dist-info/METADATA
kern-0.0.14.dist-info/WHEEL
kern-0.0.14.dist-info/entry_points.txt
kern-0.0.14.dist-info/top_level.txt
kern-0.0.14.dist-info/RECORD
