Metadata-Version: 2.1
Name: kern
Version: 0.0.14
Summary: Unix kernel for Software 2.0
Author-email: Jason Wilkes <notarealdeveloper@gmail.com>, Michael Chen <michael.chen@aicadium.ai>
Project-URL: source, https://github.com/notarealdeveloper/kern
Project-URL: download, https://pypi.org/project/kern/#files
Requires-Dist: filetype
Requires-Dist: pypandoc
Requires-Dist: pypdf
Requires-Dist: validators
Requires-Dist: requests
Requires-Dist: bs4
Requires-Dist: pytest
Requires-Dist: Pillow
Requires-Dist: av
Requires-Dist: transformers
Requires-Dist: assure
Requires-Dist: mmry
